{
  "name": "무적힐러2",
  "tolerance": 0,
  "description": null,
  "points": [
    {
      "dx": 0,
      "dy": 0,
      "color": [
        0,
        95,
        153
      ],
      "tolerance": null
    },
    {
      "dx": 37,
      "dy": 0,
      "color": [
        0,
        95,
        153
      ],
      "tolerance": null
    },
    {
      "dx": 24,
      "dy": 1,
      "color": [
        48,
        54,
        53
      ],
      "tolerance": null
    },
    {
      "dx": 23,
      "dy": 1,
      "color": [
        28,
        30,
        32
      ],
      "tolerance": null
    },
    {
      "dx": 11,
      "dy": 1,
      "color": [
        106,
        161,
        160
      ],
      "tolerance": null
    },
    {
      "dx": 29,
      "dy": 2,
      "color": [
        28,
        141,
        128
      ],
      "tolerance": null
    },
    {
      "dx": 18,
      "dy": 11,
      "color": [
        27,
        29,
        31
      ],
      "tolerance": null
    },
    {
      "dx": 18,
      "dy": 12,
      "color": [
        22,
        22,
        24
      ],
      "tolerance": null
    }
  ]
}